metalmental_logger/__init__.py
metalmental_logger/logger.py
metalmental_logger-0.7.1.dist-info/LICENSE
metalmental_logger-0.7.1.dist-info/METADATA
metalmental_logger-0.7.1.dist-info/WHEEL
metalmental_logger-0.7.1.dist-info/top_level.txt
metalmental_logger-0.7.1.dist-info/RECORD
