Metadata-Version: 2.1
Name: metalmental_logger
Version: 0.7.1
Summary: A simple logger library that outputs logs to both standard output and a file by specifying the log level
Home-page: https://github.com/Flupinochan/MetalMentalPythonLogger
Author: MetalMental
Author-email: flupino@metalmental.net
License: MIT
Classifier: Programming Language :: Python :: 3.8
Classifier: Programming Language :: Python :: 3.9
Classifier: Programming Language :: Python :: 3.10
Classifier: Programming Language :: Python :: 3.11
Classifier: Programming Language :: Python :: 3.12
Classifier: Programming Language :: Python :: 3.13
Classifier: License :: OSI Approved :: MIT License
Classifier: Operating System :: OS Independent
Requires-Python: >=3.8
License-File: LICENSE
